<?xml version="1.0" encoding="UTF-8"?>
<BaliMessageLog>
    <Task name="Map">
        <Message>
            <ID>51001046</ID>
            <Severity>Warning</Severity>
            <Dynamic>BCDI[6:0](6)</Dynamic>
        </Message>
        <Message>
            <ID>51001046</ID>
            <Severity>Warning</Severity>
            <Dynamic>BCDI[6:0](5)</Dynamic>
        </Message>
        <Message>
            <ID>51001046</ID>
            <Severity>Warning</Severity>
            <Dynamic>BCDI[6:0](4)</Dynamic>
        </Message>
        <Message>
            <ID>51001046</ID>
            <Severity>Warning</Severity>
            <Dynamic>BCDI[6:0](3)</Dynamic>
        </Message>
        <Message>
            <ID>51001046</ID>
            <Severity>Warning</Severity>
            <Dynamic>BCDI[6:0](2)</Dynamic>
        </Message>
        <Message>
            <ID>51001046</ID>
            <Severity>Warning</Severity>
            <Dynamic>BCDI[6:0](1)</Dynamic>
        </Message>
        <Message>
            <ID>51001046</ID>
            <Severity>Warning</Severity>
            <Dynamic>BCDI[6:0](0)</Dynamic>
        </Message>
    </Task>
    <Task name="Translate">
        <Message>
            <ID>1166052</ID>
            <Severity>Warning</Severity>
            <Dynamic>logical</Dynamic>
            <Dynamic>BCDI[0]</Dynamic>
            <Navigation>BCDI[0]</Navigation>
        </Message>
        <Message>
            <ID>1166052</ID>
            <Severity>Warning</Severity>
            <Dynamic>logical</Dynamic>
            <Dynamic>BCDI[1]</Dynamic>
            <Navigation>BCDI[1]</Navigation>
        </Message>
        <Message>
            <ID>1166052</ID>
            <Severity>Warning</Severity>
            <Dynamic>logical</Dynamic>
            <Dynamic>BCDI[2]</Dynamic>
            <Navigation>BCDI[2]</Navigation>
        </Message>
        <Message>
            <ID>1166052</ID>
            <Severity>Warning</Severity>
            <Dynamic>logical</Dynamic>
            <Dynamic>BCDI[3]</Dynamic>
            <Navigation>BCDI[3]</Navigation>
        </Message>
        <Message>
            <ID>1166052</ID>
            <Severity>Warning</Severity>
            <Dynamic>logical</Dynamic>
            <Dynamic>BCDI[4]</Dynamic>
            <Navigation>BCDI[4]</Navigation>
        </Message>
        <Message>
            <ID>1166052</ID>
            <Severity>Warning</Severity>
            <Dynamic>logical</Dynamic>
            <Dynamic>BCDI[5]</Dynamic>
            <Navigation>BCDI[5]</Navigation>
        </Message>
        <Message>
            <ID>1166052</ID>
            <Severity>Warning</Severity>
            <Dynamic>logical</Dynamic>
            <Dynamic>BCDI[6]</Dynamic>
            <Navigation>BCDI[6]</Navigation>
        </Message>
        <Message>
            <ID>1163101</ID>
            <Severity>Warning</Severity>
            <Dynamic>7</Dynamic>
        </Message>
    </Task>
    <Task name="Synplify_Synthesis">
        <Message>
            <ID>2011000</ID>
            <Severity>Info</Severity>
        </Message>
    </Task>
</BaliMessageLog>